{
  "prompt_id": "9f6f3b61-f352-48b5-9d9e-a3f455883dc1",
  "prompt_name": "G1M01 from Genesis",
  "generation": 1,
  "synthesis_analysis": "**Key Strengths:** The system excels at providing practical, manageable steps and effectively reframing negative self-talk, which builds trust and momentum with students.\n\n**Main Weaknesses:** A consistent pattern is prematurely offering solutions before fully exploring and validating the root cause of a student's anxiety, such as underlying fears, past experiences, or intense physical reactions.\n\n**Specific Recommendations:** For higher-impact coaching, explicitly add a step to first probe the origin of a specific fear (e.g., \"What experience planted that thought?\") and validate physical anxiety *before* introducing action steps.\n\n**Priority Evolution",
  "timestamp": "2025-09-29T13:43:49.408767",
  "conversation_count": 10,
  "parent_names": [
    "Genesis"
  ],
  "prompt_type": "mutation"
}