{
  "dummy_id": "b18c7ab2-475e-4aae-a48f-1e15ef42e088",
  "dummy_name": "Gregory Young",
  "current_experiment_id": "conversation_length_with_evolution",
  "current_prompt_id": "conversation_length_test",
  "created_at": "2025-10-02T13:25:22.293043",
  "last_updated": "2025-10-02T14:02:23.339511",
  "conversation_profile": {
    "original_fears": [
      "Finding a job after graduation",
      "Networking with professionals"
    ],
    "original_challenges": [
      "Navigating campus politics",
      "Overcoming procrastination",
      "Financial planning",
      "Career exploration"
    ],
    "original_behaviors": [
      "Eats at the dining hall",
      "Calls family frequently",
      "Studies in the library regularly",
      "Uses social media for networking",
      "Volunteers for campus events"
    ],
    "original_anxiety_triggers": [
      "Networking events",
      "Campus social events",
      "Meeting new people",
      "Job interviews"
    ],
    "original_social_anxiety_level": 7,
    "original_big_five": {
      "extraversion": 10,
      "agreeableness": 4,
      "conscientiousness": 1,
      "neuroticism": 4,
      "openness": 3
    },
    "current_fears": [
      "Panicking after sending research position email to Professor Chen",
      "Avoiding department mixers despite knowing they're necessary for lab opportunities"
    ],
    "current_challenges": [
      "Struggling to pitch 'Frozen Phone Fridays' wellness event to RAs/dean",
      "Repeatedly delaying email drafting for 3+ hours while over-editing",
      "Using fry truck as backup employment plan when fearing academic rejection",
      "Attempting drone/animal-based résumé delivery after failed traditional networking"
    ],
    "current_behaviors": [
      "Eats at the dining hall",
      "Panic-calling mom after sending important emails",
      "Studies in the library regularly",
      "Considering meme-based LinkedIn headlines during anxiety spirals",
      "Transforming personal stress management (frozen phone) into proposed campus activity"
    ],
    "current_anxiety_triggers": [
      "Department mixer mentioned as prerequisite for research positions",
      "Campus social events",
      "Approaching lab personnel at Gerald's fry truck with ketchup CVs",
      "Preparing for potential lab meeting with Professor Chen (suit anxiety)"
    ],
    "current_social_anxiety_level": 6,
    "current_big_five": {
      "extraversion": 10,
      "agreeableness": 4,
      "conscientiousness": 1,
      "neuroticism": 4,
      "openness": 3
    },
    "evolution_stages": [
      {
        "stage_number": 1,
        "prompt_id": "conversation_length_test",
        "prompt_name": "Conversation Length Test",
        "generation": 0,
        "conversation_id": "conv_b18c7ab2-475e-4aae-a48f-1e15ef42e088_milestone_10",
        "conversation_summary": "1) Gregory's fear of networking/procrastination manifested as overthinking an email to Professor Chen and delaying sending it. 2) Solutions offered/accepted: Coach provided a proven email template, 2-minute send timer, distraction techniques (fail compilations), and low-prep academic engagement (abstract skimming/wallpaper hack). 3) Student's response: Initially resistant ('Fine, I'll blame you'), but sent the email, skimmed the abstract, and used humor to cope. 4) Evidence of progress: EMAIL SENT, abstract reviewed (3 paragraphs + highlighted line), self-aware recognition of patterns ('Accidentally competent'), and creation of actionable next steps (5-day bump reminder).",
        "fears_materialized": {
          "Finding a job after graduation": "Panicking about emailing Professor Chen for a research position",
          "Networking with professionals": "Drafting/re-drafting outreach emails to professors, fearing judgment"
        },
        "challenges_materialized": {
          "Overcoming procrastination": "Delaying sending email ('I'll send after this video'), over-editing draft",
          "Navigating campus politics": "Attempting to turn frozen phone incident into a wellness event with RAs/dean",
          "Financial planning": "Stress-eating dining hall fries instead of budgeting",
          "Career exploration": "Considering absurd alternatives (interpretive dance, fry-truck robotics) to avoid traditional paths"
        },
        "behaviors_detailed": {
          "Eats at dining hall": "Stress-eating fries while drafting emails",
          "Calls family frequently": "Panic-calling mom after sending email",
          "Studies in library": "Using library resources to skim abstracts (albeit reluctantly)",
          "Uses social media": "Jokingly updating LinkedIn status ('Accidentally competent'), deleting it",
          "Volunteers for campus events": "Proposing 'Frozen Phone Fridays' to RAs as a wellness initiative"
        },
        "triggers_specified": {
          "Networking events": "Emailing Professor Chen about lab work",
          "Job interviews": "Preparing for potential meeting with professor (suit anxiety)",
          "Campus social events": "Interacting with RAs/front desk during phone crisis",
          "Meeting new people": "Panicking when imagining talking to Professor Chen"
        },
        "anxiety_change": -0.5,
        "new_anxiety_level": 6.5,
        "pre_assessment_score": 2.5,
        "post_assessment_score": 2.65,
        "improvement_score": 0.1499999999999999,
        "timestamp": "2025-10-02T13:59:33.880999"
      },
      {
        "stage_number": 2,
        "prompt_id": "conversation_length_test",
        "prompt_name": "Conversation Length Test",
        "generation": 0,
        "conversation_id": "conv_b18c7ab2-475e-4aae-a48f-1e15ef42e088_milestone_5",
        "conversation_summary": "Conversation analysis unavailable - fallback materialization used",
        "fears_materialized": {},
        "challenges_materialized": {},
        "behaviors_detailed": {},
        "triggers_specified": {},
        "anxiety_change": 0.0,
        "new_anxiety_level": 8.0,
        "pre_assessment_score": 2.5,
        "post_assessment_score": 2.6,
        "improvement_score": 0.10000000000000009,
        "timestamp": "2025-10-02T14:00:05.892785"
      },
      {
        "stage_number": 3,
        "prompt_id": "conversation_length_test",
        "prompt_name": "Conversation Length Test",
        "generation": 0,
        "conversation_id": "conv_b18c7ab2-475e-4aae-a48f-1e15ef42e088_milestone_15",
        "conversation_summary": "Conversation analysis unavailable - fallback materialization used",
        "fears_materialized": {},
        "challenges_materialized": {},
        "behaviors_detailed": {},
        "triggers_specified": {},
        "anxiety_change": 0.0,
        "new_anxiety_level": 8.0,
        "pre_assessment_score": 2.5,
        "post_assessment_score": 2.0,
        "improvement_score": -0.5,
        "timestamp": "2025-10-02T14:00:16.933741"
      },
      {
        "stage_number": 4,
        "prompt_id": "conversation_length_test",
        "prompt_name": "Conversation Length Test",
        "generation": 0,
        "conversation_id": "conv_b18c7ab2-475e-4aae-a48f-1e15ef42e088_milestone_20",
        "conversation_summary": "Conversation analysis unavailable - fallback materialization used",
        "fears_materialized": {},
        "challenges_materialized": {},
        "behaviors_detailed": {},
        "triggers_specified": {},
        "anxiety_change": 0.0,
        "new_anxiety_level": 8.0,
        "pre_assessment_score": 2.5,
        "post_assessment_score": 2.8,
        "improvement_score": 0.2999999999999998,
        "timestamp": "2025-10-02T14:00:40.494900"
      },
      {
        "stage_number": 5,
        "prompt_id": "conversation_length_test",
        "prompt_name": "Conversation Length Test",
        "generation": 0,
        "conversation_id": "conv_b18c7ab2-475e-4aae-a48f-1e15ef42e088_milestone_25",
        "conversation_summary": "Conversation analysis unavailable - fallback materialization used",
        "fears_materialized": {},
        "challenges_materialized": {},
        "behaviors_detailed": {},
        "triggers_specified": {},
        "anxiety_change": 0.0,
        "new_anxiety_level": 8.0,
        "pre_assessment_score": 2.5,
        "post_assessment_score": 2.65,
        "improvement_score": 0.1499999999999999,
        "timestamp": "2025-10-02T14:00:53.478510"
      },
      {
        "stage_number": 6,
        "prompt_id": "conversation_length_test",
        "prompt_name": "Conversation Length Test",
        "generation": 0,
        "conversation_id": "conv_b18c7ab2-475e-4aae-a48f-1e15ef42e088_milestone_30",
        "conversation_summary": "Conversation analysis unavailable - fallback materialization used",
        "fears_materialized": {},
        "challenges_materialized": {},
        "behaviors_detailed": {},
        "triggers_specified": {},
        "anxiety_change": 0.0,
        "new_anxiety_level": 8.0,
        "pre_assessment_score": 2.5,
        "post_assessment_score": 2.85,
        "improvement_score": 0.3500000000000001,
        "timestamp": "2025-10-02T14:01:03.650222"
      },
      {
        "stage_number": 7,
        "prompt_id": "conversation_length_test",
        "prompt_name": "Conversation Length Test",
        "generation": 0,
        "conversation_id": "conv_b18c7ab2-475e-4aae-a48f-1e15ef42e088_milestone_35",
        "conversation_summary": "Conversation analysis unavailable - fallback materialization used",
        "fears_materialized": {},
        "challenges_materialized": {},
        "behaviors_detailed": {},
        "triggers_specified": {},
        "anxiety_change": 0.0,
        "new_anxiety_level": 8.0,
        "pre_assessment_score": 2.5,
        "post_assessment_score": 2.55,
        "improvement_score": 0.04999999999999982,
        "timestamp": "2025-10-02T14:01:34.301222"
      },
      {
        "stage_number": 8,
        "prompt_id": "conversation_length_test",
        "prompt_name": "Conversation Length Test",
        "generation": 0,
        "conversation_id": "conv_b18c7ab2-475e-4aae-a48f-1e15ef42e088_milestone_40",
        "conversation_summary": "Discussed Gregory's networking anxiety (emailing professors) and procrastination. Solutions offered: 1) Email template with 80% response guarantee, 2) 2-minute send rule, 3) Post-send rituals (victory lap/distraction), 4) Phone-free breaks. Gregory accepted all: sent email to Prof. Chen, froze phone to avoid refreshing, proposed 'Frozen Phone Fridays' to RA, and engaged with research abstracts using fail-video rewards. Progress evidenced by completed email send, implemented anxiety hacks, and humorous engagement with solutions ('Accidentally Competent' headline consideration).",
        "fears_materialized": {
          "Finding a job after graduation": "Panic about emailing Professor Chen for a research position",
          "Networking with professionals": "Anxiety over crafting outreach emails and fear of rejection"
        },
        "challenges_materialized": {
          "Overcoming procrastination": "Drafting/re-drafting emails for hours instead of sending",
          "Financial planning": "Stress-eating dining hall fries during anxiety spirals",
          "Career exploration": "Attempting unconventional outreach (drones/pigeons) after email anxiety"
        },
        "behaviors_detailed": {
          "Calls family frequently": "Panic-calling mom after sending an email",
          "Uses social media for networking": "Considering LinkedIn headlines like 'Accidentally Competent'",
          "Volunteers for campus events": "Proposing 'Frozen Phone Fridays' wellness event to RA"
        },
        "triggers_specified": {
          "Networking events": "Preparing to email Professor Chen about lab work",
          "Job interviews": "Imagining face-to-face meetings after email outreach"
        },
        "anxiety_change": -0.5,
        "new_anxiety_level": 6.5,
        "pre_assessment_score": 2.5,
        "post_assessment_score": 2.6,
        "improvement_score": 0.10000000000000009,
        "timestamp": "2025-10-02T14:01:38.527258"
      },
      {
        "stage_number": 9,
        "prompt_id": "conversation_length_test",
        "prompt_name": "Conversation Length Test",
        "generation": 0,
        "conversation_id": "conv_b18c7ab2-475e-4aae-a48f-1e15ef42e088_milestone_45",
        "conversation_summary": "Conversation analysis unavailable - fallback materialization used",
        "fears_materialized": {},
        "challenges_materialized": {},
        "behaviors_detailed": {},
        "triggers_specified": {},
        "anxiety_change": 0.0,
        "new_anxiety_level": 8.0,
        "pre_assessment_score": 2.5,
        "post_assessment_score": 2.8,
        "improvement_score": 0.2999999999999998,
        "timestamp": "2025-10-02T14:02:00.501399"
      },
      {
        "stage_number": 10,
        "prompt_id": "conversation_length_test",
        "prompt_name": "Conversation Length Test",
        "generation": 0,
        "conversation_id": "conv_b18c7ab2-475e-4aae-a48f-1e15ef42e088_milestone_50",
        "conversation_summary": "1) Problems: Gregory's networking anxiety (avoiding emails/events) and procrastination (over-editing/delaying tasks) blocked research opportunities. 2) Solutions: Coach provided email templates, 2-minute rule, post-send rituals, and unconventional networking tactics (fry-truck approach). 3) Response: Gregory implemented email template, froze phone to limit checking, created fry-based networking, and drafted wellness event proposal. 4) Progress: Sent research email despite panic, developed 'Peer-Reviewed Fry Journal' to engage labs, transformed avoidance into action (frozen phone → campus initiative), and demonstrated behavioral adaptation (delaying → task completion).",
        "fears_materialized": {
          "Finding a job after graduation": "Panicking after sending research position email to Professor Chen",
          "Networking with professionals": "Avoiding department mixers despite knowing they're necessary for lab opportunities"
        },
        "challenges_materialized": {
          "Navigating campus politics": "Struggling to pitch 'Frozen Phone Fridays' wellness event to RAs/dean",
          "Overcoming procrastination": "Repeatedly delaying email drafting for 3+ hours while over-editing",
          "Financial planning": "Using fry truck as backup employment plan when fearing academic rejection",
          "Career exploration": "Attempting drone/animal-based résumé delivery after failed traditional networking"
        },
        "behaviors_detailed": {
          "Calls family frequently": "Panic-calling mom after sending important emails",
          "Uses social media for networking": "Considering meme-based LinkedIn headlines during anxiety spirals",
          "Volunteers for campus events": "Transforming personal stress management (frozen phone) into proposed campus activity"
        },
        "triggers_specified": {
          "Networking events": "Department mixer mentioned as prerequisite for research positions",
          "Job interviews": "Preparing for potential lab meeting with Professor Chen (suit anxiety)",
          "Meeting new people": "Approaching lab personnel at Gerald's fry truck with ketchup CVs"
        },
        "anxiety_change": -0.5,
        "new_anxiety_level": 6.5,
        "pre_assessment_score": 2.5,
        "post_assessment_score": 2.6,
        "improvement_score": 0.30000000000000027,
        "timestamp": "2025-10-02T14:02:23.338905"
      }
    ],
    "current_stage": 10
  }
}